[
    {
        "name": "Pamela Bray",
        "age": 28
    },
    {
        "name": "Gregory Smith",
        "age": 30,
        "country": null
    },
    {
        "name": "Patricia Johnston",
        "age": 48
    },
    {
        "name": "April Waller",
        "country": "US"
    },
    {
        "name": "Hannah Jones",
        "age": null,
        "country": "US"
    },
    {
        "name": "Victoria Valdez",
        "age": 51,
        "country": "US"
    },
    {
        "name": "Howard Carpenter",
        "age": 27,
        "country": "JP"
    },
    {
        "name": "Jeremiah Cabrera",
        "age": 52,
        "country": "BR"
    },
    {
        "name": "Lucas Phillips",
        "age": 24,
        "country": "JP"
    },
    {
        "name": "Jack Olsen",
        "age": 28,
        "country": "DE"
    },
    {
        "name": "Mary Curtis",
        "age": 27,
        "country": "BR"
    },
    {
        "name": "Michael Rice",
        "age": 27,
        "country": "BR"
    },
    {
        "name": "Jesus Clark",
        "age": 45,
        "country": "UK"
    },
    {
        "name": "Rhonda Novak",
        "age": 50,
        "country": "UK"
    },
    {
        "name": "Derek Beard",
        "age": 46,
        "country": "BR"
    },
    {
        "name": "Rachael Richards",
        "age": 57,
        "country": "BR"
    },
    {
        "name": "Ronald Gray",
        "age": 32,
        "country": "AU"
    },
    {
        "name": "Katrina Mcclain",
        "age": 49,
        "country": "BR"
    },
    {
        "name": "Gregg Walters",
        "age": 35,
        "country": "AU"
    },
    {
        "name": "Christopher Nichols",
        "age": 32,
        "country": "UK"
    },
    {
        "name": "Jason Rodriguez",
        "age": 50,
        "country": "BR"
    },
    {
        "name": "Adam Hodge",
        "age": 21,
        "country": "JP"
    },
    {
        "name": "Laura Carter",
        "age": 54,
        "country": "CA"
    },
    {
        "name": "Amanda Newton",
        "age": 34,
        "country": "DE"
    },
    {
        "name": "Bailey Coleman",
        "age": 40,
        "country": "AU"
    },
    {
        "name": "Tara Carter",
        "age": 36,
        "country": "AU"
    },
    {
        "name": "Dr. Amanda Hunt",
        "age": 47,
        "country": "AU"
    },
    {
        "name": "Austin Stephens",
        "age": 54,
        "country": "UK"
    },
    {
        "name": "Christopher Mccoy",
        "age": 57,
        "country": "UK"
    },
    {
        "name": "Diane Hansen",
        "age": 18,
        "country": "BR"
    },
    {
        "name": "Tammy Allen",
        "age": 44,
        "country": "CA"
    },
    {
        "name": "Angel Salazar",
        "age": 32,
        "country": "DE"
    },
    {
        "name": "Victor Fuller",
        "age": 23,
        "country": "AU"
    },
    {
        "name": "Adam Barker",
        "age": 45,
        "country": "JP"
    },
    {
        "name": "John Grimes",
        "age": 50,
        "country": "DE"
    },
    {
        "name": "Chad Anderson",
        "age": 54,
        "country": "JP"
    },
    {
        "name": "Erin Roberts",
        "age": 34,
        "country": "AU"
    },
    {
        "name": "Andrew Vazquez",
        "age": 36,
        "country": "FR"
    },
    {
        "name": "John Medina",
        "age": 38,
        "country": "CA"
    },
    {
        "name": "Tiffany Horne MD",
        "age": 55,
        "country": "JP"
    },
    {
        "name": "Ashley Green",
        "age": 40,
        "country": "CA"
    },
    {
        "name": "Sarah Peck",
        "age": 46,
        "country": "BR"
    },
    {
        "name": "Monica Cabrera",
        "age": 29,
        "country": "FR"
    },
    {
        "name": "Anthony Arnold",
        "age": 36,
        "country": "DE"
    },
    {
        "name": "Joshua Howell",
        "age": 19,
        "country": "JP"
    },
    {
        "name": "Andrea Parker",
        "age": 33,
        "country": "CA"
    },
    {
        "name": "Brian Villarreal",
        "age": 36,
        "country": "UK"
    },
    {
        "name": "Anthony Brown",
        "age": 25,
        "country": "DE"
    },
    {
        "name": "Rachel Velasquez",
        "age": 27,
        "country": "FR"
    },
    {
        "name": "Donald Chaney",
        "age": 37,
        "country": "FR"
    },
    {
        "name": "Mrs. Crystal Nicholson DVM",
        "age": 56,
        "country": "UK"
    },
    {
        "name": "Susan Graham",
        "age": 19,
        "country": "US"
    },
    {
        "name": "Chloe Medina",
        "age": 26,
        "country": "UK"
    },
    {
        "name": "Karen Strong",
        "age": 58,
        "country": "UK"
    },
    {
        "name": "Taylor Medina",
        "age": 44,
        "country": "CA"
    },
    {
        "name": "Kristina Soto",
        "age": 29,
        "country": "AU"
    },
    {
        "name": "Jay Hunt",
        "age": 50,
        "country": "JP"
    },
    {
        "name": "Susan Griffith",
        "age": 48,
        "country": "UK"
    },
    {
        "name": "John Duke",
        "age": 42,
        "country": "FR"
    },
    {
        "name": "Erika Chambers",
        "age": 33,
        "country": "JP"
    },
    {
        "name": "Sabrina Davis",
        "age": 41,
        "country": "AU"
    },
    {
        "name": "Christy Oconnell",
        "age": 34,
        "country": "DE"
    },
    {
        "name": "Erin Pittman",
        "age": 47,
        "country": "CA"
    },
    {
        "name": "Carl Valencia",
        "age": 43,
        "country": "FR"
    },
    {
        "name": "Larry Johnson",
        "age": 38,
        "country": "US"
    },
    {
        "name": "Austin Lucas",
        "age": 58,
        "country": "BR"
    },
    {
        "name": "Patrick Griffith",
        "age": 51,
        "country": "JP"
    },
    {
        "name": "Eric Miller",
        "age": 37,
        "country": "DE"
    },
    {
        "name": "Melissa Banks",
        "age": 42,
        "country": "FR"
    },
    {
        "name": "Joshua Hudson",
        "age": 56,
        "country": "AU"
    },
    {
        "name": "Stephanie Norton",
        "age": 53,
        "country": "CA"
    },
    {
        "name": "Kelsey Forbes",
        "age": 38,
        "country": "DE"
    },
    {
        "name": "Jennifer Evans",
        "age": 46,
        "country": "JP"
    },
    {
        "name": "Michael Martin",
        "age": 47,
        "country": "FR"
    },
    {
        "name": "David Greene",
        "age": 44,
        "country": "UK"
    },
    {
        "name": "Aaron Soto",
        "age": 27,
        "country": "JP"
    },
    {
        "name": "Richard King MD",
        "age": 42,
        "country": "DE"
    },
    {
        "name": "Richard Moore",
        "age": 57,
        "country": "DE"
    },
    {
        "name": "Marissa Guzman",
        "age": 59,
        "country": "AU"
    },
    {
        "name": "Thomas Bennett",
        "age": 27,
        "country": "BR"
    },
    {
        "name": "Kaitlyn Valenzuela",
        "age": 39,
        "country": "UK"
    },
    {
        "name": "Chad Flores",
        "age": 33,
        "country": "AU"
    },
    {
        "name": "Mary Ruiz",
        "age": 33,
        "country": "BR"
    },
    {
        "name": "Tracy Price",
        "age": 21,
        "country": "JP"
    },
    {
        "name": "Rachel Solis",
        "age": 52,
        "country": "BR"
    },
    {
        "name": "Brooke Hill",
        "age": 56,
        "country": "US"
    },
    {
        "name": "Carol Sherman",
        "age": 46,
        "country": "BR"
    },
    {
        "name": "Alexandra Jordan",
        "age": 47,
        "country": "JP"
    },
    {
        "name": "Jeremy Delgado",
        "age": 46,
        "country": "US"
    },
    {
        "name": "Nicole Nichols",
        "age": 24,
        "country": "UK"
    },
    {
        "name": "Nicholas Mcgee",
        "age": 21,
        "country": "AU"
    },
    {
        "name": "Sherri Strickland",
        "age": 35,
        "country": "AU"
    },
    {
        "name": "Timothy Pierce",
        "age": 18,
        "country": "FR"
    },
    {
        "name": "Wanda Davis",
        "age": 24,
        "country": "BR"
    },
    {
        "name": "Matthew Davis",
        "age": 60,
        "country": "FR"
    },
    {
        "name": "Brenda Lee",
        "age": 23,
        "country": "FR"
    },
    {
        "name": "Richard Wright",
        "age": 55,
        "country": "US"
    },
    {
        "name": "Jamie Walker",
        "age": 53,
        "country": "UK"
    },
    {
        "name": "Philip Dixon",
        "age": 53,
        "country": "UK"
    },
    {
        "name": "Virginia Hughes",
        "age": 24,
        "country": "CA"
    },
    {
        "name": "Thomas Armstrong",
        "age": 23,
        "country": "US"
    },
    {
        "name": "Hannah Gomez",
        "age": 22,
        "country": "JP"
    },
    {
        "name": "Shawn Sanders",
        "age": 35,
        "country": "FR"
    },
    {
        "name": "Benjamin Campbell",
        "age": 59,
        "country": "JP"
    },
    {
        "name": "Adam Simpson",
        "age": 23,
        "country": "FR"
    },
    {
        "name": "Mary Wilson",
        "age": 58,
        "country": "DE"
    },
    {
        "name": "Kelli Carson",
        "age": 54,
        "country": "US"
    },
    {
        "name": "Tyler Deleon",
        "age": 27,
        "country": "UK"
    },
    {
        "name": "Melissa Hernandez",
        "age": 39,
        "country": "FR"
    },
    {
        "name": "Nathan Greer DVM",
        "age": 51,
        "country": "CA"
    },
    {
        "name": "Amanda Wolfe",
        "age": 34,
        "country": "BR"
    },
    {
        "name": "Brian Rodriguez",
        "age": 56,
        "country": "FR"
    },
    {
        "name": "Chloe Brown",
        "age": 28,
        "country": "UK"
    },
    {
        "name": "Jeffery Perez",
        "age": 41,
        "country": "DE"
    },
    {
        "name": "Mark Weiss",
        "age": 59,
        "country": "DE"
    },
    {
        "name": "Anthony Jackson",
        "age": 26,
        "country": "CA"
    },
    {
        "name": "Dr. Christopher Russell",
        "age": 35,
        "country": "AU"
    },
    {
        "name": "Tony Hernandez",
        "age": 37,
        "country": "DE"
    },
    {
        "name": "Christian Rogers",
        "age": 19,
        "country": "CA"
    },
    {
        "name": "Donald Kramer",
        "age": 30,
        "country": "UK"
    },
    {
        "name": "Sandra Williamson",
        "age": 38,
        "country": "FR"
    },
    {
        "name": "Kevin Li",
        "age": 46,
        "country": "US"
    },
    {
        "name": "Tiffany King",
        "age": 34,
        "country": "DE"
    },
    {
        "name": "Brittany Allen",
        "age": 27,
        "country": "US"
    },
    {
        "name": "Brian Reid",
        "age": 37,
        "country": "AU"
    },
    {
        "name": "Donald Mendez",
        "age": 35,
        "country": "BR"
    },
    {
        "name": "Valerie Crosby",
        "age": 36,
        "country": "UK"
    },
    {
        "name": "James Wilson",
        "age": 26,
        "country": "US"
    },
    {
        "name": "Erin Beck",
        "age": 36,
        "country": "UK"
    },
    {
        "name": "Jason Barrera",
        "age": 22,
        "country": "AU"
    },
    {
        "name": "Jacob Lopez",
        "age": 23,
        "country": "FR"
    },
    {
        "name": "James Kennedy",
        "age": 57,
        "country": "US"
    },
    {
        "name": "Tyler West",
        "age": 27,
        "country": "UK"
    },
    {
        "name": "Hayden Mullins",
        "age": 60,
        "country": "BR"
    },
    {
        "name": "Dr. Jennifer Hardin",
        "age": 20,
        "country": "DE"
    },
    {
        "name": "Alex Jones",
        "age": 59,
        "country": "FR"
    },
    {
        "name": "Christian Wilson",
        "age": 19,
        "country": "FR"
    },
    {
        "name": "Harold Delgado",
        "age": 45,
        "country": "FR"
    },
    {
        "name": "Samuel Walters",
        "age": 19,
        "country": "CA"
    },
    {
        "name": "Sharon Yang",
        "age": 31,
        "country": "JP"
    },
    {
        "name": "Diane Woods",
        "age": 44,
        "country": "FR"
    },
    {
        "name": "Joseph Jones",
        "age": 56,
        "country": "JP"
    },
    {
        "name": "Christina Nguyen",
        "age": 52,
        "country": "BR"
    },
    {
        "name": "Tonya Hodges",
        "age": 60,
        "country": "DE"
    },
    {
        "name": "Stephanie Martinez",
        "age": 59,
        "country": "US"
    },
    {
        "name": "William Ruiz",
        "age": 28,
        "country": "CA"
    },
    {
        "name": "Julian Duncan",
        "age": 31,
        "country": "FR"
    },
    {
        "name": "Peter Gaines",
        "age": 43,
        "country": "JP"
    },
    {
        "name": "Alejandra Taylor",
        "age": 29,
        "country": "AU"
    },
    {
        "name": "Jonathan Thomas",
        "age": 60,
        "country": "UK"
    },
    {
        "name": "Kevin Tate",
        "age": 47,
        "country": "BR"
    },
    {
        "name": "William Middleton",
        "age": 29,
        "country": "FR"
    },
    {
        "name": "Megan Ramirez",
        "age": 34,
        "country": "JP"
    },
    {
        "name": "Meghan James",
        "age": 34,
        "country": "FR"
    },
    {
        "name": "Alyssa Walter",
        "age": 20,
        "country": "JP"
    },
    {
        "name": "Patrick Ray",
        "age": 18,
        "country": "DE"
    },
    {
        "name": "Jeremiah Mcclain",
        "age": 59,
        "country": "FR"
    },
    {
        "name": "Taylor Ballard",
        "age": 59,
        "country": "CA"
    },
    {
        "name": "Erin Bryant",
        "age": 49,
        "country": "AU"
    },
    {
        "name": "Alicia Sanchez",
        "age": 34,
        "country": "DE"
    },
    {
        "name": "Gary Espinoza",
        "age": 50,
        "country": "JP"
    },
    {
        "name": "Allen Hernandez",
        "age": 27,
        "country": "FR"
    },
    {
        "name": "Thomas Pena",
        "age": 39,
        "country": "AU"
    },
    {
        "name": "Lori Rivera",
        "age": 25,
        "country": "JP"
    },
    {
        "name": "Sara Smith",
        "age": 56,
        "country": "CA"
    },
    {
        "name": "Aaron Smith",
        "age": 60,
        "country": "JP"
    },
    {
        "name": "Richard Greene",
        "age": 37,
        "country": "AU"
    },
    {
        "name": "Jesus Stevens",
        "age": 40,
        "country": "JP"
    },
    {
        "name": "Miguel Yates",
        "age": 56,
        "country": "US"
    },
    {
        "name": "Luis Cole",
        "age": 18,
        "country": "DE"
    },
    {
        "name": "Sarah Smith",
        "age": 21,
        "country": "AU"
    },
    {
        "name": "Samuel Perry",
        "age": 23,
        "country": "BR"
    },
    {
        "name": "Raymond Hayes",
        "age": 60,
        "country": "AU"
    },
    {
        "name": "Andrea Zamora",
        "age": 58,
        "country": "CA"
    },
    {
        "name": "Ashley Reyes",
        "age": 49,
        "country": "BR"
    },
    {
        "name": "Crystal Simpson",
        "age": 37,
        "country": "JP"
    },
    {
        "name": "Kimberly Nelson",
        "age": 59,
        "country": "FR"
    },
    {
        "name": "Hayley Fleming",
        "age": 57,
        "country": "JP"
    },
    {
        "name": "Ronald Richards",
        "age": 36,
        "country": "JP"
    },
    {
        "name": "Jessica Juarez",
        "age": 58,
        "country": "CA"
    },
    {
        "name": "Rodney Mason",
        "age": 45,
        "country": "AU"
    },
    {
        "name": "Jane Cobb",
        "age": 23,
        "country": "CA"
    },
    {
        "name": "Laura Mcdonald",
        "age": 42,
        "country": "DE"
    },
    {
        "name": "Frank Russell",
        "age": 33,
        "country": "CA"
    },
    {
        "name": "Mr. Matthew Logan",
        "age": 49,
        "country": "JP"
    },
    {
        "name": "Anthony Powers",
        "age": 26,
        "country": "AU"
    },
    {
        "name": "Erica Reeves",
        "age": 18,
        "country": "BR"
    },
    {
        "name": "Erik Nelson",
        "age": 59,
        "country": "CA"
    },
    {
        "name": "Candice Baker",
        "age": 36,
        "country": "BR"
    },
    {
        "name": "Sandra Odonnell",
        "age": 54,
        "country": "BR"
    },
    {
        "name": "Victoria Stewart",
        "age": 31,
        "country": "FR"
    },
    {
        "name": "Mr. George Prince MD",
        "age": 54,
        "country": "CA"
    },
    {
        "name": "Daniel Mendez",
        "age": 27,
        "country": "BR"
    },
    {
        "name": "Brett Travis",
        "age": 58,
        "country": "US"
    },
    {
        "name": "Ebony Watts",
        "age": 58,
        "country": "FR"
    },
    {
        "name": "Jorge Best",
        "age": 52,
        "country": "FR"
    },
    {
        "name": "Kayla Gomez",
        "age": 24,
        "country": "UK"
    },
    {
        "name": "Jacqueline Lane",
        "age": 31,
        "country": "CA"
    },
    {
        "name": "Deborah Graves",
        "age": 60,
        "country": "AU"
    },
    {
        "name": "Joshua Hall",
        "age": 38,
        "country": "JP"
    },
    {
        "name": "Lisa Hunter",
        "age": 24,
        "country": "CA"
    },
    {
        "name": "Anna Riley",
        "age": 45,
        "country": "UK"
    },
    {
        "name": "Kimberly Mcmahon",
        "age": 60,
        "country": "BR"
    },
    {
        "name": "Anna Dunn",
        "age": 27,
        "country": "US"
    },
    {
        "name": "Lisa Davis",
        "age": 27,
        "country": "JP"
    },
    {
        "name": "Casey Park",
        "age": 49,
        "country": "AU"
    },
    {
        "name": "Adam Decker",
        "age": 54,
        "country": "UK"
    },
    {
        "name": "Donald Simmons",
        "age": 41,
        "country": "JP"
    },
    {
        "name": "Kelly Obrien",
        "age": 57,
        "country": "AU"
    },
    {
        "name": "Krista Johnson",
        "age": 30,
        "country": "FR"
    },
    {
        "name": "Samuel Hoffman",
        "age": 39,
        "country": "JP"
    },
    {
        "name": "Lauren Wallace",
        "age": 28,
        "country": "BR"
    },
    {
        "name": "Gavin Wade",
        "age": 47,
        "country": "DE"
    },
    {
        "name": "Eddie Boyd",
        "age": 20,
        "country": "BR"
    },
    {
        "name": "Seth Garcia",
        "age": 58,
        "country": "CA"
    },
    {
        "name": "Katherine Robinson",
        "age": 53,
        "country": "US"
    },
    {
        "name": "Jennifer Espinoza",
        "age": 34,
        "country": "FR"
    },
    {
        "name": "Thomas Richmond",
        "age": 39,
        "country": "US"
    },
    {
        "name": "Jeremy Mitchell PhD",
        "age": 24,
        "country": "CA"
    },
    {
        "name": "Scott Terry",
        "age": 39,
        "country": "CA"
    },
    {
        "name": "Kristina Johnson",
        "age": 59,
        "country": "FR"
    },
    {
        "name": "Austin Brown",
        "age": 57,
        "country": "DE"
    },
    {
        "name": "Matthew Terrell",
        "age": 22,
        "country": "JP"
    },
    {
        "name": "Kelly Smith",
        "age": 26,
        "country": "DE"
    },
    {
        "name": "Alexander Lowe",
        "age": 40,
        "country": "JP"
    },
    {
        "name": "Paul Bell",
        "age": 32,
        "country": "CA"
    },
    {
        "name": "Ian Vance",
        "age": 28,
        "country": "JP"
    },
    {
        "name": "Rebecca Davis",
        "age": 50,
        "country": "JP"
    },
    {
        "name": "Billy Lamb",
        "age": 50,
        "country": "CA"
    },
    {
        "name": "Richard Carpenter",
        "age": 42,
        "country": "BR"
    },
    {
        "name": "Beth Campbell",
        "age": 27,
        "country": "FR"
    },
    {
        "name": "Kimberly Kent",
        "age": 42,
        "country": "CA"
    },
    {
        "name": "Robyn Smith",
        "age": 19,
        "country": "FR"
    },
    {
        "name": "Samantha Bonilla",
        "age": 27,
        "country": "FR"
    },
    {
        "name": "Jessica Serrano",
        "age": 34,
        "country": "FR"
    },
    {
        "name": "Stephanie Martin",
        "age": 39,
        "country": "BR"
    },
    {
        "name": "Mary Quinn",
        "age": 39,
        "country": "US"
    },
    {
        "name": "Kathryn Kelly",
        "age": 59,
        "country": "FR"
    },
    {
        "name": "John Horn",
        "age": 48,
        "country": "US"
    },
    {
        "name": "Michael West",
        "age": 34,
        "country": "DE"
    },
    {
        "name": "Lisa Houston",
        "age": 44,
        "country": "DE"
    },
    {
        "name": "Erik Juarez",
        "age": 22,
        "country": "FR"
    },
    {
        "name": "Scott Fry",
        "age": 32,
        "country": "CA"
    },
    {
        "name": "Antonio Livingston",
        "age": 19,
        "country": "DE"
    },
    {
        "name": "Samuel Williams",
        "age": 54,
        "country": "BR"
    },
    {
        "name": "Jennifer Jackson",
        "age": 51,
        "country": "UK"
    },
    {
        "name": "Matthew Wright",
        "age": 30,
        "country": "DE"
    },
    {
        "name": "Craig Martin",
        "age": 21,
        "country": "DE"
    },
    {
        "name": "Amanda Walton",
        "age": 43,
        "country": "JP"
    },
    {
        "name": "Marcia Vazquez",
        "age": 48,
        "country": "JP"
    },
    {
        "name": "Duane Moore",
        "age": 57,
        "country": "JP"
    },
    {
        "name": "Kathryn Wells",
        "age": 38,
        "country": "CA"
    },
    {
        "name": "Melissa Hall",
        "age": 20,
        "country": "BR"
    },
    {
        "name": "Terri Garrett",
        "age": 28,
        "country": "JP"
    },
    {
        "name": "Frances Pratt",
        "age": 30,
        "country": "CA"
    },
    {
        "name": "Harry Terry",
        "age": 38,
        "country": "FR"
    },
    {
        "name": "Taylor Turner",
        "age": 36,
        "country": "JP"
    },
    {
        "name": "Jessica Cummings",
        "age": 27,
        "country": "UK"
    },
    {
        "name": "David Reynolds",
        "age": 41,
        "country": "AU"
    },
    {
        "name": "Dustin Mahoney",
        "age": 19,
        "country": "US"
    },
    {
        "name": "Thomas Duffy",
        "age": 60,
        "country": "AU"
    },
    {
        "name": "Andrea Nguyen",
        "age": 54,
        "country": "JP"
    },
    {
        "name": "Christopher Sullivan",
        "age": 34,
        "country": "US"
    },
    {
        "name": "Mrs. Rachel Butler MD",
        "age": 25,
        "country": "JP"
    },
    {
        "name": "John Valencia",
        "age": 59,
        "country": "FR"
    },
    {
        "name": "Brian Burns",
        "age": 37,
        "country": "US"
    },
    {
        "name": "Mary Cunningham",
        "age": 51,
        "country": "US"
    },
    {
        "name": "Jessica Patton",
        "age": 60,
        "country": "AU"
    },
    {
        "name": "Matthew Horn",
        "age": 18,
        "country": "UK"
    },
    {
        "name": "Leah Sanders",
        "age": 50,
        "country": "UK"
    },
    {
        "name": "Mr. David Cruz MD",
        "age": 45,
        "country": "DE"
    },
    {
        "name": "Lorraine Andrade",
        "age": 39,
        "country": "CA"
    },
    {
        "name": "Rose Coleman",
        "age": 60,
        "country": "JP"
    },
    {
        "name": "Michael Collins",
        "age": 21,
        "country": "DE"
    },
    {
        "name": "Jennifer Shaw",
        "age": 52,
        "country": "CA"
    },
    {
        "name": "Ryan Jackson",
        "age": 41,
        "country": "CA"
    },
    {
        "name": "Sherri Allen",
        "age": 21,
        "country": "DE"
    },
    {
        "name": "Matthew Kline",
        "age": 30,
        "country": "BR"
    },
    {
        "name": "David Romero",
        "age": 36,
        "country": "JP"
    },
    {
        "name": "Luis Martinez",
        "age": 50,
        "country": "FR"
    },
    {
        "name": "Amanda Evans",
        "age": 50,
        "country": "FR"
    },
    {
        "name": "John Graves",
        "age": 33,
        "country": "FR"
    },
    {
        "name": "Michael Williams",
        "age": 29,
        "country": "JP"
    },
    {
        "name": "Emily Delacruz",
        "age": 24,
        "country": "CA"
    },
    {
        "name": "Monica Williams",
        "age": 29,
        "country": "DE"
    },
    {
        "name": "Cindy Watson",
        "age": 58,
        "country": "AU"
    },
    {
        "name": "Leslie Keith",
        "age": 41,
        "country": "FR"
    },
    {
        "name": "John Fernandez",
        "age": 24,
        "country": "UK"
    },
    {
        "name": "Vanessa Robinson",
        "age": 24,
        "country": "US"
    },
    {
        "name": "James Taylor",
        "age": 48,
        "country": "CA"
    },
    {
        "name": "Jeffrey Weiss",
        "age": 28,
        "country": "AU"
    },
    {
        "name": "Mitchell Smith",
        "age": 39,
        "country": "CA"
    },
    {
        "name": "Nathaniel Reed",
        "age": 47,
        "country": "CA"
    },
    {
        "name": "Christine Hill",
        "age": 59,
        "country": "DE"
    },
    {
        "name": "Amber Morris",
        "age": 35,
        "country": "CA"
    },
    {
        "name": "Paul Lewis",
        "age": 50,
        "country": "DE"
    },
    {
        "name": "John Mathis",
        "age": 36,
        "country": "BR"
    },
    {
        "name": "Charlene Schultz",
        "age": 21,
        "country": "AU"
    },
    {
        "name": "Jamie Smith",
        "age": 54,
        "country": "AU"
    },
    {
        "name": "Kara Wilkinson",
        "age": 58,
        "country": "US"
    },
    {
        "name": "David Berry",
        "age": 50,
        "country": "US"
    },
    {
        "name": "Amanda Peters",
        "age": 43,
        "country": "UK"
    },
    {
        "name": "Shane Crawford",
        "age": 20,
        "country": "AU"
    },
    {
        "name": "Melissa Mason",
        "age": 38,
        "country": "DE"
    },
    {
        "name": "Charles Turner",
        "age": 28,
        "country": "DE"
    },
    {
        "name": "Matthew Peterson",
        "age": 58,
        "country": "BR"
    },
    {
        "name": "Evan Ortega",
        "age": 49,
        "country": "JP"
    },
    {
        "name": "Wendy Fleming",
        "age": 20,
        "country": "BR"
    },
    {
        "name": "Dennis Ray DDS",
        "age": 58,
        "country": "US"
    },
    {
        "name": "Laura Ashley",
        "age": 37,
        "country": "JP"
    },
    {
        "name": "Tara Martinez",
        "age": 58,
        "country": "US"
    },
    {
        "name": "Lauren Miller",
        "age": 26,
        "country": "US"
    },
    {
        "name": "Jessica Kane",
        "age": 54,
        "country": "JP"
    },
    {
        "name": "Robert Burgess",
        "age": 47,
        "country": "BR"
    },
    {
        "name": "Nicholas Walker",
        "age": 44,
        "country": "CA"
    },
    {
        "name": "Steven Ferguson",
        "age": 49,
        "country": "US"
    },
    {
        "name": "Amy Morse",
        "age": 22,
        "country": "UK"
    },
    {
        "name": "Samuel Byrd",
        "age": 21,
        "country": "UK"
    },
    {
        "name": "Shirley Mata",
        "age": 25,
        "country": "DE"
    },
    {
        "name": "Sarah Mckenzie",
        "age": 58,
        "country": "BR"
    },
    {
        "name": "Devin Casey",
        "age": 36,
        "country": "DE"
    },
    {
        "name": "Kendra Dalton",
        "age": 44,
        "country": "FR"
    },
    {
        "name": "Kelsey Landry",
        "age": 48,
        "country": "JP"
    },
    {
        "name": "Mrs. Christina Price MD",
        "age": 42,
        "country": "JP"
    },
    {
        "name": "Heather Russell",
        "age": 52,
        "country": "UK"
    },
    {
        "name": "Kimberly Williamson",
        "age": 33,
        "country": "FR"
    },
    {
        "name": "Billy Cobb",
        "age": 46,
        "country": "CA"
    },
    {
        "name": "Christopher Parker",
        "age": 19,
        "country": "DE"
    },
    {
        "name": "Patrick Green",
        "age": 47,
        "country": "UK"
    },
    {
        "name": "George Harrell",
        "age": 24,
        "country": "AU"
    },
    {
        "name": "Abigail Smith",
        "age": 56,
        "country": "FR"
    },
    {
        "name": "Daniel Moses",
        "age": 22,
        "country": "DE"
    },
    {
        "name": "Nicholas Rodriguez",
        "age": 53,
        "country": "UK"
    },
    {
        "name": "Kimberly Trujillo",
        "age": 28,
        "country": "JP"
    },
    {
        "name": "Justin Walters",
        "age": 42,
        "country": "BR"
    },
    {
        "name": "Alexander Campbell",
        "age": 43,
        "country": "FR"
    },
    {
        "name": "Dakota Gonzalez",
        "age": 30,
        "country": "CA"
    },
    {
        "name": "Paul Yu",
        "age": 20,
        "country": "US"
    },
    {
        "name": "Christopher Sims",
        "age": 58,
        "country": "US"
    },
    {
        "name": "Dillon Hunter",
        "age": 28,
        "country": "UK"
    },
    {
        "name": "Bridget Lynch",
        "age": 26,
        "country": "AU"
    },
    {
        "name": "Lisa Burns",
        "age": 45,
        "country": "BR"
    },
    {
        "name": "Corey Chase",
        "age": 32,
        "country": "JP"
    },
    {
        "name": "Tracy Jones",
        "age": 46,
        "country": "JP"
    },
    {
        "name": "Laura Arroyo",
        "age": 51,
        "country": "FR"
    },
    {
        "name": "Sharon Callahan",
        "age": 22,
        "country": "DE"
    },
    {
        "name": "Kim Garcia",
        "age": 57,
        "country": "AU"
    },
    {
        "name": "Ryan Sullivan",
        "age": 23,
        "country": "US"
    },
    {
        "name": "Veronica Whitehead",
        "age": 27,
        "country": "US"
    },
    {
        "name": "Linda Clark",
        "age": 26,
        "country": "DE"
    },
    {
        "name": "Dennis Anderson",
        "age": 45,
        "country": "US"
    },
    {
        "name": "Tracy Hale",
        "age": 22,
        "country": "AU"
    },
    {
        "name": "Elizabeth Ramirez",
        "age": 19,
        "country": "CA"
    },
    {
        "name": "Scott Nelson",
        "age": 59,
        "country": "FR"
    },
    {
        "name": "Carol Robinson",
        "age": 33,
        "country": "FR"
    },
    {
        "name": "Mrs. Jessica Payne",
        "age": 35,
        "country": "JP"
    },
    {
        "name": "Eric Cole",
        "age": 60,
        "country": "UK"
    },
    {
        "name": "James Martin Jr.",
        "age": 20,
        "country": "AU"
    },
    {
        "name": "Amanda Thomas",
        "age": 42,
        "country": "US"
    },
    {
        "name": "Caleb Harris",
        "age": 20,
        "country": "FR"
    },
    {
        "name": "Erin Bates",
        "age": 29,
        "country": "BR"
    },
    {
        "name": "Brittney Lopez",
        "age": 39,
        "country": "FR"
    },
    {
        "name": "Kathleen Williams",
        "age": 50,
        "country": "BR"
    },
    {
        "name": "Joe Jenkins",
        "age": 24,
        "country": "FR"
    },
    {
        "name": "Cathy Harrell",
        "age": 53,
        "country": "DE"
    },
    {
        "name": "Jeremy Waters",
        "age": 33,
        "country": "JP"
    },
    {
        "name": "Gail West",
        "age": 36,
        "country": "FR"
    },
    {
        "name": "Joshua Johnson",
        "age": 21,
        "country": "UK"
    },
    {
        "name": "Brandon Bailey",
        "age": 27,
        "country": "CA"
    },
    {
        "name": "Karen Moore",
        "age": 43,
        "country": "JP"
    },
    {
        "name": "Brett Mccann",
        "age": 55,
        "country": "CA"
    },
    {
        "name": "Manuel Snyder",
        "age": 30,
        "country": "DE"
    },
    {
        "name": "Thomas Miller",
        "age": 46,
        "country": "AU"
    },
    {
        "name": "Juan Carter",
        "age": 59,
        "country": "UK"
    },
    {
        "name": "Carolyn Martinez",
        "age": 33,
        "country": "DE"
    },
    {
        "name": "Diana Davis",
        "age": 38,
        "country": "DE"
    },
    {
        "name": "Dr. Craig Gonzales",
        "age": 31,
        "country": "BR"
    },
    {
        "name": "William Murray",
        "age": 32,
        "country": "AU"
    },
    {
        "name": "Angel Marquez",
        "age": 28,
        "country": "CA"
    },
    {
        "name": "Dawn Shannon",
        "age": 19,
        "country": "CA"
    },
    {
        "name": "Pamela Barnes",
        "age": 57,
        "country": "US"
    },
    {
        "name": "Bill Scott",
        "age": 45,
        "country": "AU"
    },
    {
        "name": "Philip Dean",
        "age": 22,
        "country": "CA"
    },
    {
        "name": "Laura Morrison",
        "age": 45,
        "country": "JP"
    },
    {
        "name": "Joshua Rosales",
        "age": 57,
        "country": "BR"
    },
    {
        "name": "Kimberly Davis",
        "age": 44,
        "country": "CA"
    },
    {
        "name": "Lawrence Tran",
        "age": 26,
        "country": "DE"
    },
    {
        "name": "Debra Perez",
        "age": 21,
        "country": "UK"
    },
    {
        "name": "Patrick Nelson",
        "age": 32,
        "country": "US"
    },
    {
        "name": "Donna Shaw",
        "age": 43,
        "country": "US"
    },
    {
        "name": "Melissa Martin",
        "age": 32,
        "country": "US"
    },
    {
        "name": "Richard Harmon",
        "age": 28,
        "country": "AU"
    },
    {
        "name": "Kathleen Miller DDS",
        "age": 55,
        "country": "FR"
    },
    {
        "name": "Nathaniel Glenn",
        "age": 59,
        "country": "US"
    },
    {
        "name": "Susan Harris",
        "age": 37,
        "country": "FR"
    },
    {
        "name": "Jason Williams",
        "age": 51,
        "country": "FR"
    },
    {
        "name": "Wendy Garcia",
        "age": 50,
        "country": "CA"
    },
    {
        "name": "Kerri Velez",
        "age": 47,
        "country": "FR"
    },
    {
        "name": "Matthew Spears",
        "age": 58,
        "country": "AU"
    },
    {
        "name": "Dr. David Turner",
        "age": 35,
        "country": "CA"
    },
    {
        "name": "Jonathan Gonzalez",
        "age": 34,
        "country": "AU"
    },
    {
        "name": "Maria Martin",
        "age": 53,
        "country": "CA"
    },
    {
        "name": "Daniel Soto",
        "age": 37,
        "country": "AU"
    },
    {
        "name": "Patricia Barton",
        "age": 36,
        "country": "UK"
    },
    {
        "name": "Stephen Tapia",
        "age": 24,
        "country": "US"
    },
    {
        "name": "Brittany Graves",
        "age": 21,
        "country": "US"
    },
    {
        "name": "Leslie Spencer",
        "age": 51,
        "country": "AU"
    },
    {
        "name": "Anthony Scott",
        "age": 20,
        "country": "JP"
    },
    {
        "name": "Joyce Simpson",
        "age": 20,
        "country": "JP"
    },
    {
        "name": "Laura Perkins",
        "age": 25,
        "country": "FR"
    },
    {
        "name": "Sarah Dixon",
        "age": 52,
        "country": "UK"
    },
    {
        "name": "Kelly Dennis",
        "age": 20,
        "country": "DE"
    },
    {
        "name": "Angela Chandler",
        "age": 58,
        "country": "US"
    },
    {
        "name": "Kyle Bowman",
        "age": 31,
        "country": "US"
    },
    {
        "name": "Jordan Mason",
        "age": 54,
        "country": "BR"
    },
    {
        "name": "Joshua Monroe",
        "age": 35,
        "country": "FR"
    },
    {
        "name": "Derek Howard",
        "age": 50,
        "country": "BR"
    },
    {
        "name": "Andrea Jones",
        "age": 37,
        "country": "DE"
    },
    {
        "name": "Marc Owens",
        "age": 51,
        "country": "DE"
    },
    {
        "name": "Kimberly Ryan",
        "age": 57,
        "country": "US"
    },
    {
        "name": "Michael Mcknight",
        "age": 42,
        "country": "DE"
    },
    {
        "name": "Brianna Bennett",
        "age": 56,
        "country": "BR"
    },
    {
        "name": "Jennifer Matthews",
        "age": 41,
        "country": "US"
    },
    {
        "name": "Jennifer Campbell",
        "age": 38,
        "country": "CA"
    },
    {
        "name": "Audrey Williams DVM",
        "age": 37,
        "country": "FR"
    },
    {
        "name": "Erica Abbott",
        "age": 57,
        "country": "JP"
    },
    {
        "name": "Denise Ramos",
        "age": 18,
        "country": "AU"
    },
    {
        "name": "Amy Reyes",
        "age": 39,
        "country": "FR"
    },
    {
        "name": "Nicholas Davis",
        "age": 38,
        "country": "US"
    },
    {
        "name": "Megan Andrews",
        "age": 56,
        "country": "DE"
    },
    {
        "name": "Tamara Levine DDS",
        "age": 57,
        "country": "US"
    },
    {
        "name": "Mr. Shane Gonzalez",
        "age": 39,
        "country": "US"
    },
    {
        "name": "Emily Harris",
        "age": 55,
        "country": "CA"
    },
    {
        "name": "Katherine Reyes",
        "age": 46,
        "country": "CA"
    },
    {
        "name": "Samantha Munoz",
        "age": 57,
        "country": "CA"
    },
    {
        "name": "Kelly Day",
        "age": 52,
        "country": "DE"
    },
    {
        "name": "Jamie Black",
        "age": 57,
        "country": "AU"
    },
    {
        "name": "Kayla Davis",
        "age": 24,
        "country": "UK"
    },
    {
        "name": "Jessica Gonzalez",
        "age": 46,
        "country": "UK"
    },
    {
        "name": "Kevin Smith",
        "age": 54,
        "country": "JP"
    },
    {
        "name": "Margaret Butler",
        "age": 50,
        "country": "US"
    },
    {
        "name": "Arthur Wilcox",
        "age": 55,
        "country": "UK"
    },
    {
        "name": "Zachary Mercer",
        "age": 31,
        "country": "BR"
    },
    {
        "name": "Barbara Barrett",
        "age": 50,
        "country": "CA"
    },
    {
        "name": "Jessica Miles",
        "age": 34,
        "country": "BR"
    },
    {
        "name": "Heidi Rose",
        "age": 34,
        "country": "FR"
    },
    {
        "name": "Thomas Mayo",
        "age": 25,
        "country": "UK"
    },
    {
        "name": "Mrs. Samantha Harris",
        "age": 49,
        "country": "AU"
    },
    {
        "name": "Alexis Ferguson",
        "age": 20,
        "country": "BR"
    },
    {
        "name": "Scott Haas",
        "age": 28,
        "country": "UK"
    },
    {
        "name": "William Barr",
        "age": 22,
        "country": "FR"
    },
    {
        "name": "Preston Howell",
        "age": 18,
        "country": "CA"
    },
    {
        "name": "Angela Hernandez",
        "age": 40,
        "country": "CA"
    },
    {
        "name": "Madeline Brown DDS",
        "age": 51,
        "country": "FR"
    },
    {
        "name": "Melvin Castro",
        "age": 43,
        "country": "DE"
    },
    {
        "name": "Darren Boyd",
        "age": 23,
        "country": "DE"
    },
    {
        "name": "Michael Hunt",
        "age": 25,
        "country": "CA"
    },
    {
        "name": "Autumn Molina",
        "age": 20,
        "country": "CA"
    },
    {
        "name": "Brittany Turner",
        "age": 43,
        "country": "DE"
    },
    {
        "name": "Allen Espinoza",
        "age": 25,
        "country": "CA"
    },
    {
        "name": "Louis Lee",
        "age": 22,
        "country": "CA"
    },
    {
        "name": "Vanessa Houston",
        "age": 47,
        "country": "CA"
    },
    {
        "name": "Michelle Bryant",
        "age": 49,
        "country": "DE"
    },
    {
        "name": "Kara White",
        "age": 36,
        "country": "US"
    },
    {
        "name": "Mackenzie Myers",
        "age": 58,
        "country": "US"
    },
    {
        "name": "Adam Goodwin",
        "age": 55,
        "country": "AU"
    },
    {
        "name": "Mary Martin",
        "age": 22,
        "country": "FR"
    },
    {
        "name": "Norman Harmon",
        "age": 19,
        "country": "JP"
    },
    {
        "name": "Michael Wallace",
        "age": 46,
        "country": "DE"
    },
    {
        "name": "Cristian Hendricks",
        "age": 23,
        "country": "US"
    },
    {
        "name": "Sheena Torres",
        "age": 22,
        "country": "BR"
    },
    {
        "name": "Brooke Rose",
        "age": 46,
        "country": "DE"
    },
    {
        "name": "Joseph Mckinney",
        "age": 21,
        "country": "BR"
    },
    {
        "name": "Jon Navarro",
        "age": 26,
        "country": "DE"
    },
    {
        "name": "Rebecca Alexander",
        "age": 26,
        "country": "JP"
    },
    {
        "name": "Marissa Walker",
        "age": 31,
        "country": "UK"
    },
    {
        "name": "Brooke Cross",
        "age": 36,
        "country": "JP"
    },
    {
        "name": "Samantha Gilbert",
        "age": 38,
        "country": "FR"
    },
    {
        "name": "John Santos",
        "age": 49,
        "country": "US"
    },
    {
        "name": "Samuel Griffith",
        "age": 19,
        "country": "CA"
    },
    {
        "name": "Melanie Torres",
        "age": 41,
        "country": "UK"
    },
    {
        "name": "Paul Daniels",
        "age": 59,
        "country": "CA"
    },
    {
        "name": "Timothy Buchanan",
        "age": 33,
        "country": "CA"
    },
    {
        "name": "Tim Nelson",
        "age": 18,
        "country": "JP"
    },
    {
        "name": "Ashley Sloan",
        "age": 52,
        "country": "US"
    },
    {
        "name": "Jeffrey Phillips",
        "age": 45,
        "country": "AU"
    },
    {
        "name": "Edward Johnson",
        "age": 44,
        "country": "UK"
    },
    {
        "name": "James Castro",
        "age": 58,
        "country": "US"
    },
    {
        "name": "Brandon Pham",
        "age": 58,
        "country": "US"
    },
    {
        "name": "Jonathan Gaines",
        "age": 24,
        "country": "AU"
    },
    {
        "name": "William Elliott",
        "age": 31,
        "country": "AU"
    },
    {
        "name": "Ronald Hill",
        "age": 38,
        "country": "UK"
    },
    {
        "name": "Andrea Miller",
        "age": 29,
        "country": "BR"
    },
    {
        "name": "Elizabeth Whitehead",
        "age": 41,
        "country": "BR"
    },
    {
        "name": "Rachel Diaz",
        "age": 48,
        "country": "DE"
    },
    {
        "name": "Sara Williams",
        "age": 24,
        "country": "DE"
    },
    {
        "name": "Jamie Bishop",
        "age": 54,
        "country": "US"
    },
    {
        "name": "Keith Adams",
        "age": 27,
        "country": "AU"
    },
    {
        "name": "Kenneth Newton",
        "age": 43,
        "country": "AU"
    },
    {
        "name": "Jessica Simmons",
        "age": 55,
        "country": "US"
    },
    {
        "name": "Hannah Castro",
        "age": 23,
        "country": "JP"
    },
    {
        "name": "Emily Brown",
        "age": 53,
        "country": "BR"
    },
    {
        "name": "Lee Buck",
        "age": 21,
        "country": "BR"
    },
    {
        "name": "Anita Alvarado",
        "age": 27,
        "country": "FR"
    },
    {
        "name": "Ryan Lee",
        "age": 57,
        "country": "DE"
    },
    {
        "name": "Cheryl Daugherty",
        "age": 39,
        "country": "AU"
    },
    {
        "name": "Amanda Middleton",
        "age": 46,
        "country": "JP"
    },
    {
        "name": "Ann Hardin",
        "age": 29,
        "country": "AU"
    },
    {
        "name": "Christopher Moreno",
        "age": 56,
        "country": "CA"
    },
    {
        "name": "Angela Bullock",
        "age": 59,
        "country": "CA"
    },
    {
        "name": "Gregory Serrano",
        "age": 32,
        "country": "FR"
    },
    {
        "name": "Kelly Rodriguez",
        "age": 40,
        "country": "AU"
    },
    {
        "name": "Mary Freeman",
        "age": 28,
        "country": "CA"
    },
    {
        "name": "Destiny Kim",
        "age": 41,
        "country": "CA"
    },
    {
        "name": "Mrs. Jessica Oconnell",
        "age": 51,
        "country": "CA"
    },
    {
        "name": "Jamie Perez",
        "age": 31,
        "country": "AU"
    },
    {
        "name": "Ryan Martinez",
        "age": 48,
        "country": "JP"
    },
    {
        "name": "Collin Wolf",
        "age": 40,
        "country": "FR"
    },
    {
        "name": "April Page",
        "age": 46,
        "country": "DE"
    },
    {
        "name": "Jason Hernandez",
        "age": 48,
        "country": "UK"
    },
    {
        "name": "Jonathan Jones",
        "age": 49,
        "country": "AU"
    },
    {
        "name": "Travis Romero",
        "age": 34,
        "country": "US"
    },
    {
        "name": "Joe Turner",
        "age": 47,
        "country": "CA"
    },
    {
        "name": "Dawn Lambert",
        "age": 32,
        "country": "US"
    },
    {
        "name": "Luis Bates",
        "age": 54,
        "country": "JP"
    },
    {
        "name": "Rebecca Moody",
        "age": 60,
        "country": "AU"
    },
    {
        "name": "Katrina Waller",
        "age": 40,
        "country": "AU"
    },
    {
        "name": "Christopher Martinez",
        "age": 56,
        "country": "CA"
    },
    {
        "name": "Zachary Wall",
        "age": 47,
        "country": "US"
    },
    {
        "name": "Samuel Stewart",
        "age": 59,
        "country": "CA"
    },
    {
        "name": "Jose Simpson",
        "age": 28,
        "country": "AU"
    },
    {
        "name": "Nicole Cole",
        "age": 47,
        "country": "UK"
    },
    {
        "name": "Elizabeth Sullivan",
        "age": 22,
        "country": "AU"
    },
    {
        "name": "Mark Thompson",
        "age": 33,
        "country": "CA"
    },
    {
        "name": "Charles Simmons",
        "age": 35,
        "country": "BR"
    },
    {
        "name": "Tabitha Phillips",
        "age": 20,
        "country": "AU"
    },
    {
        "name": "Scott Gates",
        "age": 37,
        "country": "FR"
    },
    {
        "name": "Jason Williams",
        "age": 32,
        "country": "UK"
    },
    {
        "name": "Amy Greene",
        "age": 45,
        "country": "BR"
    },
    {
        "name": "Brad Day",
        "age": 39,
        "country": "AU"
    },
    {
        "name": "Seth Nolan",
        "age": 40,
        "country": "BR"
    },
    {
        "name": "Darrell Melton",
        "age": 57,
        "country": "BR"
    },
    {
        "name": "Sandra Walker",
        "age": 35,
        "country": "CA"
    },
    {
        "name": "Stuart Patterson",
        "age": 40,
        "country": "JP"
    },
    {
        "name": "Allison Harris",
        "age": 46,
        "country": "FR"
    },
    {
        "name": "Mary Carlson",
        "age": 35,
        "country": "US"
    },
    {
        "name": "James Aguilar",
        "age": 30,
        "country": "UK"
    },
    {
        "name": "Nicholas Stewart",
        "age": 56,
        "country": "CA"
    },
    {
        "name": "Melissa Benton",
        "age": 60,
        "country": "AU"
    },
    {
        "name": "Dakota Ramirez",
        "age": 57,
        "country": "US"
    },
    {
        "name": "Megan Morales",
        "age": 41,
        "country": "UK"
    },
    {
        "name": "Cynthia Hess",
        "age": 26,
        "country": "DE"
    },
    {
        "name": "Kyle Skinner",
        "age": 53,
        "country": "JP"
    },
    {
        "name": "Janice Bailey",
        "age": 23,
        "country": "AU"
    },
    {
        "name": "Justin Norton",
        "age": 59,
        "country": "BR"
    },
    {
        "name": "Sheryl Chen",
        "age": 47,
        "country": "JP"
    },
    {
        "name": "Beverly Graves",
        "age": 54,
        "country": "JP"
    },
    {
        "name": "Nathan Nguyen",
        "age": 55,
        "country": "BR"
    },
    {
        "name": "Kyle Rodriguez",
        "age": 52,
        "country": "UK"
    },
    {
        "name": "Crystal Morrison",
        "age": 59,
        "country": "CA"
    },
    {
        "name": "Mitchell Scott",
        "age": 47,
        "country": "BR"
    },
    {
        "name": "David Green",
        "age": 30,
        "country": "UK"
    },
    {
        "name": "Kendra Davis",
        "age": 54,
        "country": "US"
    },
    {
        "name": "Jennifer Mueller",
        "age": 23,
        "country": "UK"
    },
    {
        "name": "Edward Pham",
        "age": 26,
        "country": "UK"
    },
    {
        "name": "Martha Keith",
        "age": 32,
        "country": "FR"
    },
    {
        "name": "Zachary Herrera",
        "age": 40,
        "country": "DE"
    },
    {
        "name": "Diamond Johnson",
        "age": 56,
        "country": "US"
    },
    {
        "name": "Larry Mcintosh",
        "age": 56,
        "country": "FR"
    },
    {
        "name": "Morgan Garrison",
        "age": 46,
        "country": "US"
    },
    {
        "name": "Raymond Willis",
        "age": 31,
        "country": "JP"
    },
    {
        "name": "Alexander Gillespie",
        "age": 58,
        "country": "DE"
    },
    {
        "name": "Taylor Gordon",
        "age": 50,
        "country": "US"
    },
    {
        "name": "Gregory Jackson",
        "age": 31,
        "country": "FR"
    },
    {
        "name": "Amy Diaz",
        "age": 42,
        "country": "JP"
    },
    {
        "name": "Whitney Olson",
        "age": 20,
        "country": "US"
    },
    {
        "name": "John Wood",
        "age": 53,
        "country": "AU"
    },
    {
        "name": "Jeffrey Lopez",
        "age": 54,
        "country": "JP"
    },
    {
        "name": "Michael Fields",
        "age": 24,
        "country": "JP"
    },
    {
        "name": "Bonnie Nichols",
        "age": 23,
        "country": "UK"
    },
    {
        "name": "Rachel Baird",
        "age": 57,
        "country": "DE"
    },
    {
        "name": "Amber Arroyo",
        "age": 40,
        "country": "DE"
    },
    {
        "name": "Maria Jordan",
        "age": 26,
        "country": "JP"
    },
    {
        "name": "Karen Spencer",
        "age": 36,
        "country": "CA"
    },
    {
        "name": "Hannah Price",
        "age": 24,
        "country": "BR"
    },
    {
        "name": "Preston Harris",
        "age": 35,
        "country": "FR"
    },
    {
        "name": "Marcus Wright",
        "age": 28,
        "country": "DE"
    },
    {
        "name": "Brandon Armstrong",
        "age": 33,
        "country": "DE"
    },
    {
        "name": "Justin Taylor",
        "age": 21,
        "country": "UK"
    },
    {
        "name": "Jamie Howard",
        "age": 33,
        "country": "DE"
    },
    {
        "name": "Kathy Mcdaniel",
        "age": 29,
        "country": "DE"
    },
    {
        "name": "Nicole Thompson",
        "age": 30,
        "country": "DE"
    },
    {
        "name": "Shawn Beasley",
        "age": 48,
        "country": "JP"
    },
    {
        "name": "Nicholas Castillo",
        "age": 52,
        "country": "UK"
    },
    {
        "name": "Beth Velasquez",
        "age": 32,
        "country": "AU"
    },
    {
        "name": "Steven Dunn",
        "age": 28,
        "country": "JP"
    },
    {
        "name": "Gregory Jenkins",
        "age": 21,
        "country": "BR"
    },
    {
        "name": "Shelly Greene",
        "age": 46,
        "country": "US"
    },
    {
        "name": "Ariel Reed",
        "age": 29,
        "country": "CA"
    },
    {
        "name": "Emma Patterson",
        "age": 42,
        "country": "JP"
    },
    {
        "name": "Connie White",
        "age": 48,
        "country": "DE"
    },
    {
        "name": "Tracey Burch",
        "age": 51,
        "country": "CA"
    },
    {
        "name": "Richard Koch",
        "age": 30,
        "country": "AU"
    },
    {
        "name": "Angelica Cain",
        "age": 38,
        "country": "CA"
    },
    {
        "name": "Nicholas Flynn",
        "age": 32,
        "country": "FR"
    },
    {
        "name": "Jill Mccormick",
        "age": 52,
        "country": "DE"
    },
    {
        "name": "Lisa Jenkins",
        "age": 27,
        "country": "FR"
    },
    {
        "name": "Scott Parker",
        "age": 50,
        "country": "AU"
    },
    {
        "name": "Bryan Parsons",
        "age": 20,
        "country": "US"
    },
    {
        "name": "Rhonda Curtis",
        "age": 37,
        "country": "AU"
    },
    {
        "name": "Victoria Andrade",
        "age": 30,
        "country": "JP"
    },
    {
        "name": "Susan Bowen",
        "age": 26,
        "country": "US"
    },
    {
        "name": "Dawn Hall",
        "age": 33,
        "country": "UK"
    },
    {
        "name": "Curtis Taylor",
        "age": 24,
        "country": "UK"
    },
    {
        "name": "Shannon Haynes",
        "age": 46,
        "country": "BR"
    },
    {
        "name": "Ryan Richard",
        "age": 48,
        "country": "JP"
    },
    {
        "name": "Eric West",
        "age": 58,
        "country": "AU"
    },
    {
        "name": "Paula Ayers",
        "age": 56,
        "country": "BR"
    },
    {
        "name": "Mary Jones",
        "age": 28,
        "country": "DE"
    },
    {
        "name": "Jessica Moore",
        "age": 36,
        "country": "AU"
    },
    {
        "name": "Christopher Gordon",
        "age": 20,
        "country": "US"
    },
    {
        "name": "Tiffany Johnson",
        "age": 35,
        "country": "JP"
    },
    {
        "name": "Thomas Hart",
        "age": 45,
        "country": "AU"
    },
    {
        "name": "Dean Rogers",
        "age": 51,
        "country": "FR"
    },
    {
        "name": "Hunter Rosales",
        "age": 37,
        "country": "CA"
    },
    {
        "name": "Lisa Marquez",
        "age": 22,
        "country": "US"
    },
    {
        "name": "Mark Bates",
        "age": 46,
        "country": "US"
    },
    {
        "name": "Darren Ruiz",
        "age": 32,
        "country": "FR"
    },
    {
        "name": "Maria Mullins",
        "age": 26,
        "country": "JP"
    },
    {
        "name": "Pamela Lane",
        "age": 40,
        "country": "BR"
    },
    {
        "name": "Joshua Greene",
        "age": 59,
        "country": "UK"
    },
    {
        "name": "Jimmy Burton",
        "age": 20,
        "country": "UK"
    },
    {
        "name": "Shelley Willis",
        "age": 26,
        "country": "US"
    },
    {
        "name": "Kyle Walker",
        "age": 34,
        "country": "UK"
    },
    {
        "name": "Jacob Blackburn",
        "age": 36,
        "country": "AU"
    },
    {
        "name": "Mary Lynn",
        "age": 41,
        "country": "FR"
    },
    {
        "name": "Kurt Donaldson",
        "age": 22,
        "country": "US"
    },
    {
        "name": "Sarah Lyons",
        "age": 60,
        "country": "US"
    },
    {
        "name": "Sarah Wolf",
        "age": 30,
        "country": "JP"
    },
    {
        "name": "David Hill",
        "age": 32,
        "country": "AU"
    },
    {
        "name": "Amanda Myers",
        "age": 45,
        "country": "BR"
    },
    {
        "name": "Matthew Hernandez",
        "age": 35,
        "country": "AU"
    },
    {
        "name": "Thomas Herman",
        "age": 48,
        "country": "US"
    },
    {
        "name": "Margaret Chambers",
        "age": 31,
        "country": "DE"
    },
    {
        "name": "Corey Valdez",
        "age": 57,
        "country": "US"
    },
    {
        "name": "James Garza",
        "age": 32,
        "country": "AU"
    },
    {
        "name": "Kenneth Green",
        "age": 44,
        "country": "DE"
    },
    {
        "name": "James Gonzales",
        "age": 60,
        "country": "JP"
    },
    {
        "name": "Rebecca Sims",
        "age": 48,
        "country": "AU"
    },
    {
        "name": "Tracy Jacobs",
        "age": 47,
        "country": "DE"
    },
    {
        "name": "Kelly Huff",
        "age": 44,
        "country": "BR"
    },
    {
        "name": "Matthew Harris",
        "age": 43,
        "country": "BR"
    },
    {
        "name": "Manuel Johnson",
        "age": 36,
        "country": "DE"
    },
    {
        "name": "Brandon Cain",
        "age": 39,
        "country": "BR"
    },
    {
        "name": "Lisa Ramirez",
        "age": 51,
        "country": "CA"
    },
    {
        "name": "Jennifer Nelson",
        "age": 30,
        "country": "FR"
    },
    {
        "name": "Jennifer Phillips",
        "age": 24,
        "country": "FR"
    },
    {
        "name": "Jonathan Gonzalez",
        "age": 32,
        "country": "CA"
    },
    {
        "name": "Tracy Sullivan",
        "age": 19,
        "country": "AU"
    },
    {
        "name": "Jamie Cook",
        "age": 26,
        "country": "FR"
    },
    {
        "name": "Nicole Stokes",
        "age": 40,
        "country": "US"
    },
    {
        "name": "Nicole Medina",
        "age": 46,
        "country": "DE"
    },
    {
        "name": "Micheal Ferguson",
        "age": 57,
        "country": "AU"
    },
    {
        "name": "Jeffery Norman",
        "age": 42,
        "country": "BR"
    },
    {
        "name": "Taylor Williams",
        "age": 49,
        "country": "CA"
    },
    {
        "name": "Brandi Stone",
        "age": 51,
        "country": "US"
    },
    {
        "name": "Jose Payne",
        "age": 59,
        "country": "JP"
    },
    {
        "name": "Matthew Martin",
        "age": 35,
        "country": "CA"
    },
    {
        "name": "Erica Hanson",
        "age": 29,
        "country": "US"
    },
    {
        "name": "Seth Moore",
        "age": 30,
        "country": "JP"
    },
    {
        "name": "David Hernandez",
        "age": 27,
        "country": "DE"
    },
    {
        "name": "Amanda Miller",
        "age": 48,
        "country": "AU"
    },
    {
        "name": "Colin Hogan",
        "age": 22,
        "country": "DE"
    },
    {
        "name": "Leonard Banks",
        "age": 28,
        "country": "BR"
    },
    {
        "name": "Laura Taylor",
        "age": 20,
        "country": "BR"
    },
    {
        "name": "Cory Jones",
        "age": 54,
        "country": "BR"
    },
    {
        "name": "Gary Pruitt",
        "age": 22,
        "country": "DE"
    },
    {
        "name": "Christopher Kelly",
        "age": 47,
        "country": "AU"
    },
    {
        "name": "Lisa Barker",
        "age": 57,
        "country": "CA"
    },
    {
        "name": "Thomas Parks",
        "age": 20,
        "country": "CA"
    },
    {
        "name": "Leslie Moore MD",
        "age": 53,
        "country": "FR"
    },
    {
        "name": "Ashley Aguilar",
        "age": 22,
        "country": "FR"
    },
    {
        "name": "Elizabeth Phillips",
        "age": 44,
        "country": "DE"
    },
    {
        "name": "Amy Rodriguez",
        "age": 20,
        "country": "BR"
    },
    {
        "name": "James Scott",
        "age": 60,
        "country": "BR"
    },
    {
        "name": "Amy White",
        "age": 42,
        "country": "AU"
    },
    {
        "name": "Terry Wood",
        "age": 37,
        "country": "FR"
    },
    {
        "name": "Billy Williams",
        "age": 35,
        "country": "US"
    },
    {
        "name": "Amanda Hodges",
        "age": 42,
        "country": "DE"
    },
    {
        "name": "Ms. Jessica Reed",
        "age": 31,
        "country": "AU"
    },
    {
        "name": "Wesley Mack",
        "age": 25,
        "country": "DE"
    },
    {
        "name": "Jeremy Davis",
        "age": 18,
        "country": "AU"
    },
    {
        "name": "Grace Guzman",
        "age": 32,
        "country": "UK"
    },
    {
        "name": "Heidi Moreno",
        "age": 28,
        "country": "AU"
    },
    {
        "name": "Johnny Kerr",
        "age": 49,
        "country": "AU"
    },
    {
        "name": "Thomas Alvarado",
        "age": 47,
        "country": "UK"
    },
    {
        "name": "Alexis Fisher",
        "age": 49,
        "country": "DE"
    },
    {
        "name": "Joan Doyle",
        "age": 40,
        "country": "FR"
    },
    {
        "name": "Patricia Ferguson",
        "age": 19,
        "country": "BR"
    },
    {
        "name": "Jeffrey Adams",
        "age": 37,
        "country": "UK"
    },
    {
        "name": "Blake White",
        "age": 50,
        "country": "BR"
    },
    {
        "name": "Brian Martinez",
        "age": 22,
        "country": "DE"
    },
    {
        "name": "Kevin Jackson",
        "age": 27,
        "country": "JP"
    },
    {
        "name": "Michael Hayes",
        "age": 34,
        "country": "AU"
    },
    {
        "name": "Jason Stewart",
        "age": 43,
        "country": "AU"
    },
    {
        "name": "Jessica Williams",
        "age": 59,
        "country": "UK"
    },
    {
        "name": "William Cohen",
        "age": 34,
        "country": "JP"
    },
    {
        "name": "Erica Becker",
        "age": 39,
        "country": "FR"
    },
    {
        "name": "Dr. Ronnie Hutchinson",
        "age": 24,
        "country": "BR"
    },
    {
        "name": "Catherine Rose",
        "age": 57,
        "country": "JP"
    },
    {
        "name": "Michelle Wagner",
        "age": 51,
        "country": "AU"
    },
    {
        "name": "Kimberly Reeves",
        "age": 42,
        "country": "JP"
    },
    {
        "name": "Marc Jennings",
        "age": 43,
        "country": "US"
    },
    {
        "name": "Mrs. Kristin Richardson",
        "age": 35,
        "country": "FR"
    },
    {
        "name": "Janice Caldwell",
        "age": 55,
        "country": "CA"
    },
    {
        "name": "Brenda Murphy",
        "age": 36,
        "country": "US"
    },
    {
        "name": "Ann Goodman",
        "age": 32,
        "country": "CA"
    },
    {
        "name": "Angela Hernandez",
        "age": 26,
        "country": "FR"
    },
    {
        "name": "Chase Brown",
        "age": 35,
        "country": "CA"
    },
    {
        "name": "Lance Durham",
        "age": 45,
        "country": "DE"
    },
    {
        "name": "Kimberly Anderson",
        "age": 33,
        "country": "UK"
    },
    {
        "name": "Amy Miller",
        "age": 43,
        "country": "CA"
    },
    {
        "name": "Ronald Martinez",
        "age": 20,
        "country": "JP"
    },
    {
        "name": "Robert Rodriguez",
        "age": 38,
        "country": "DE"
    },
    {
        "name": "Sarah Coleman",
        "age": 43,
        "country": "BR"
    },
    {
        "name": "Amanda Smith",
        "age": 22,
        "country": "FR"
    },
    {
        "name": "Richard Schneider",
        "age": 47,
        "country": "UK"
    },
    {
        "name": "Shirley White",
        "age": 36,
        "country": "US"
    },
    {
        "name": "Danny Yu",
        "age": 24,
        "country": "UK"
    },
    {
        "name": "Robert Davis",
        "age": 29,
        "country": "AU"
    },
    {
        "name": "Scott Hull",
        "age": 47,
        "country": "FR"
    },
    {
        "name": "William Thomas",
        "age": 59,
        "country": "US"
    },
    {
        "name": "Brandon English",
        "age": 41,
        "country": "DE"
    },
    {
        "name": "Sean Mann",
        "age": 22,
        "country": "AU"
    },
    {
        "name": "David Reed",
        "age": 50,
        "country": "UK"
    },
    {
        "name": "Amy Hansen",
        "age": 59,
        "country": "US"
    },
    {
        "name": "Suzanne Brown",
        "age": 27,
        "country": "CA"
    },
    {
        "name": "Terrance King",
        "age": 44,
        "country": "JP"
    },
    {
        "name": "Steven Nelson",
        "age": 26,
        "country": "BR"
    },
    {
        "name": "Cynthia Dean",
        "age": 60,
        "country": "BR"
    },
    {
        "name": "Carol Gonzalez",
        "age": 40,
        "country": "DE"
    },
    {
        "name": "Angela Compton",
        "age": 58,
        "country": "JP"
    },
    {
        "name": "Brian Munoz",
        "age": 50,
        "country": "US"
    },
    {
        "name": "Sharon Clark",
        "age": 49,
        "country": "AU"
    },
    {
        "name": "Brian Higgins",
        "age": 20,
        "country": "CA"
    },
    {
        "name": "Tony Brown",
        "age": 39,
        "country": "BR"
    },
    {
        "name": "Abigail Ramirez",
        "age": 47,
        "country": "AU"
    },
    {
        "name": "Michael Johnston",
        "age": 42,
        "country": "BR"
    },
    {
        "name": "Ronald Mejia",
        "age": 51,
        "country": "AU"
    },
    {
        "name": "Julia Medina",
        "age": 19,
        "country": "DE"
    },
    {
        "name": "Cody Wiggins",
        "age": 20,
        "country": "CA"
    },
    {
        "name": "Maria Hayden",
        "age": 50,
        "country": "JP"
    },
    {
        "name": "Robert Smith",
        "age": 47,
        "country": "FR"
    },
    {
        "name": "Kelly Goodman",
        "age": 51,
        "country": "FR"
    },
    {
        "name": "Dr. Michael Ayala II",
        "age": 43,
        "country": "UK"
    },
    {
        "name": "Brett Marshall",
        "age": 34,
        "country": "JP"
    },
    {
        "name": "Joseph Estes",
        "age": 23,
        "country": "CA"
    },
    {
        "name": "Alexander Jones",
        "age": 45,
        "country": "BR"
    },
    {
        "name": "John Valdez",
        "age": 57,
        "country": "US"
    },
    {
        "name": "Nicole Benson",
        "age": 60,
        "country": "AU"
    },
    {
        "name": "Anthony Oneal",
        "age": 32,
        "country": "UK"
    },
    {
        "name": "Ricky Hodge",
        "age": 20,
        "country": "CA"
    },
    {
        "name": "Jessica Lyons",
        "age": 43,
        "country": "FR"
    },
    {
        "name": "Aaron Rodriguez",
        "age": 39,
        "country": "UK"
    },
    {
        "name": "Justin Holmes",
        "age": 21,
        "country": "AU"
    },
    {
        "name": "Sharon Estrada",
        "age": 32,
        "country": "US"
    },
    {
        "name": "Nicole Wilson",
        "age": 59,
        "country": "JP"
    },
    {
        "name": "Nicole Ortiz",
        "age": 52,
        "country": "DE"
    },
    {
        "name": "Tyler Holmes",
        "age": 53,
        "country": "FR"
    },
    {
        "name": "Andrew Gordon",
        "age": 57,
        "country": "JP"
    },
    {
        "name": "Danielle Osborne",
        "age": 57,
        "country": "UK"
    },
    {
        "name": "Tina Bautista",
        "age": 48,
        "country": "UK"
    },
    {
        "name": "Lisa Gonzales",
        "age": 50,
        "country": "BR"
    },
    {
        "name": "Elizabeth Sims",
        "age": 33,
        "country": "AU"
    },
    {
        "name": "Joshua Garcia",
        "age": 52,
        "country": "JP"
    },
    {
        "name": "Jeff Taylor",
        "age": 37,
        "country": "UK"
    },
    {
        "name": "Tina Gomez",
        "age": 34,
        "country": "JP"
    },
    {
        "name": "Jackson Bailey",
        "age": 51,
        "country": "US"
    },
    {
        "name": "Wayne Snyder",
        "age": 43,
        "country": "BR"
    },
    {
        "name": "Jeffrey Bowen",
        "age": 41,
        "country": "CA"
    },
    {
        "name": "Mary Nichols",
        "age": 35,
        "country": "DE"
    },
    {
        "name": "Anna Allen",
        "age": 59,
        "country": "DE"
    },
    {
        "name": "Ryan Dyer",
        "age": 39,
        "country": "DE"
    },
    {
        "name": "Carla Ramirez",
        "age": 52,
        "country": "FR"
    },
    {
        "name": "Craig Patel",
        "age": 20,
        "country": "UK"
    },
    {
        "name": "Holly Becker",
        "age": 52,
        "country": "US"
    },
    {
        "name": "Wanda Rios",
        "age": 49,
        "country": "DE"
    },
    {
        "name": "Walter Reid",
        "age": 29,
        "country": "BR"
    },
    {
        "name": "Mitchell Munoz",
        "age": 42,
        "country": "US"
    },
    {
        "name": "John Young",
        "age": 40,
        "country": "BR"
    },
    {
        "name": "Angela Payne",
        "age": 31,
        "country": "US"
    },
    {
        "name": "James King",
        "age": 20,
        "country": "CA"
    },
    {
        "name": "Amanda Shields",
        "age": 49,
        "country": "FR"
    },
    {
        "name": "Angela Adams",
        "age": 41,
        "country": "UK"
    },
    {
        "name": "Aaron White",
        "age": 23,
        "country": "UK"
    },
    {
        "name": "Scott Bishop",
        "age": 56,
        "country": "JP"
    },
    {
        "name": "Brian Smith",
        "age": 34,
        "country": "US"
    },
    {
        "name": "Kelly Hull",
        "age": 54,
        "country": "CA"
    },
    {
        "name": "Mr. Frederick Rivera DVM",
        "age": 34,
        "country": "BR"
    },
    {
        "name": "Kathleen Frye",
        "age": 52,
        "country": "AU"
    },
    {
        "name": "Mary White",
        "age": 22,
        "country": "JP"
    },
    {
        "name": "Russell Flores",
        "age": 33,
        "country": "UK"
    },
    {
        "name": "Grace Crawford",
        "age": 35,
        "country": "US"
    },
    {
        "name": "Vanessa Maynard",
        "age": 30,
        "country": "FR"
    },
    {
        "name": "Cynthia White",
        "age": 26,
        "country": "UK"
    },
    {
        "name": "David Hart",
        "age": 44,
        "country": "UK"
    },
    {
        "name": "Mr. Matthew Schultz",
        "age": 55,
        "country": "UK"
    },
    {
        "name": "Derek Aguilar",
        "age": 55,
        "country": "US"
    },
    {
        "name": "Dalton Richardson",
        "age": 55,
        "country": "AU"
    },
    {
        "name": "Eugene Baker",
        "age": 48,
        "country": "US"
    },
    {
        "name": "Chase Munoz",
        "age": 53,
        "country": "US"
    },
    {
        "name": "Scott Grimes",
        "age": 31,
        "country": "UK"
    },
    {
        "name": "Tony Mckenzie",
        "age": 47,
        "country": "AU"
    },
    {
        "name": "Jerry Turner",
        "age": 50,
        "country": "CA"
    },
    {
        "name": "Michael Johnson",
        "age": 39,
        "country": "US"
    },
    {
        "name": "Richard Johnson",
        "age": 35,
        "country": "AU"
    },
    {
        "name": "Laura Meyer",
        "age": 48,
        "country": "JP"
    },
    {
        "name": "Douglas Johnson",
        "age": 34,
        "country": "BR"
    },
    {
        "name": "Blake Martinez",
        "age": 51,
        "country": "FR"
    },
    {
        "name": "Erin Adams",
        "age": 54,
        "country": "US"
    },
    {
        "name": "Corey Morton",
        "age": 56,
        "country": "US"
    },
    {
        "name": "Jason Gallegos",
        "age": 40,
        "country": "DE"
    },
    {
        "name": "Laura Pena",
        "age": 21,
        "country": "BR"
    },
    {
        "name": "Jason Peters",
        "age": 23,
        "country": "UK"
    },
    {
        "name": "Jessica Harris",
        "age": 42,
        "country": "DE"
    },
    {
        "name": "Kellie Lee",
        "age": 33,
        "country": "DE"
    },
    {
        "name": "Louis Collins",
        "age": 32,
        "country": "UK"
    },
    {
        "name": "Courtney Morris",
        "age": 38,
        "country": "AU"
    },
    {
        "name": "Nicholas Hernandez",
        "age": 43,
        "country": "AU"
    },
    {
        "name": "Benjamin Smith",
        "age": 30,
        "country": "US"
    },
    {
        "name": "Matthew Boyer MD",
        "age": 51,
        "country": "UK"
    },
    {
        "name": "Lisa Williams",
        "age": 37,
        "country": "UK"
    },
    {
        "name": "Susan Williams",
        "age": 53,
        "country": "FR"
    },
    {
        "name": "Ryan Lynn",
        "age": 37,
        "country": "BR"
    },
    {
        "name": "Todd Marks",
        "age": 29,
        "country": "DE"
    },
    {
        "name": "Christina Lucas",
        "age": 55,
        "country": "CA"
    },
    {
        "name": "Jeffrey Osborne",
        "age": 37,
        "country": "AU"
    },
    {
        "name": "Jacob Ryan",
        "age": 38,
        "country": "AU"
    },
    {
        "name": "Laurie Contreras",
        "age": 42,
        "country": "US"
    },
    {
        "name": "Kyle Gonzales",
        "age": 35,
        "country": "UK"
    },
    {
        "name": "Sarah Ferguson",
        "age": 49,
        "country": "CA"
    },
    {
        "name": "Dawn Ramsey",
        "age": 36,
        "country": "JP"
    },
    {
        "name": "James Mcintyre",
        "age": 27,
        "country": "BR"
    },
    {
        "name": "Anthony Cruz",
        "age": 54,
        "country": "AU"
    },
    {
        "name": "Matthew Sellers",
        "age": 59,
        "country": "CA"
    },
    {
        "name": "Stacey Diaz",
        "age": 50,
        "country": "US"
    },
    {
        "name": "Kyle Flores",
        "age": 25,
        "country": "FR"
    },
    {
        "name": "James Scott",
        "age": 56,
        "country": "AU"
    },
    {
        "name": "Clayton Miller",
        "age": 33,
        "country": "AU"
    },
    {
        "name": "Julie Mitchell",
        "age": 30,
        "country": "FR"
    },
    {
        "name": "Carrie Thornton",
        "age": 36,
        "country": "AU"
    },
    {
        "name": "Karen Nichols",
        "age": 44,
        "country": "FR"
    },
    {
        "name": "Sheryl Duran",
        "age": 52,
        "country": "FR"
    },
    {
        "name": "Sonya Steele",
        "age": 24,
        "country": "FR"
    },
    {
        "name": "Kristina Mcdowell",
        "age": 29,
        "country": "UK"
    },
    {
        "name": "Henry Doyle",
        "age": 46,
        "country": "JP"
    },
    {
        "name": "Jessica Edwards",
        "age": 27,
        "country": "AU"
    },
    {
        "name": "David Quinn",
        "age": 47,
        "country": "CA"
    },
    {
        "name": "Robert Meadows",
        "age": 18,
        "country": "DE"
    },
    {
        "name": "Albert Dillon",
        "age": 32,
        "country": "AU"
    },
    {
        "name": "John Barron",
        "age": 32,
        "country": "FR"
    },
    {
        "name": "Jeanne Gutierrez",
        "age": 57,
        "country": "FR"
    },
    {
        "name": "Robert Brooks",
        "age": 23,
        "country": "UK"
    },
    {
        "name": "Michael Jones",
        "age": 48,
        "country": "UK"
    },
    {
        "name": "John Robinson",
        "age": 39,
        "country": "BR"
    },
    {
        "name": "Rhonda Olsen",
        "age": 55,
        "country": "BR"
    },
    {
        "name": "Richard Moss",
        "age": 22,
        "country": "DE"
    },
    {
        "name": "Henry Jackson",
        "age": 36,
        "country": "AU"
    },
    {
        "name": "Donna Carroll",
        "age": 44,
        "country": "JP"
    },
    {
        "name": "Dennis Bates",
        "age": 44,
        "country": "US"
    },
    {
        "name": "Paul Contreras",
        "age": 44,
        "country": "JP"
    },
    {
        "name": "Destiny Perez",
        "age": 25,
        "country": "UK"
    },
    {
        "name": "Marc Jones",
        "age": 38,
        "country": "DE"
    },
    {
        "name": "David Francis",
        "age": 38,
        "country": "BR"
    },
    {
        "name": "Isaac Grant",
        "age": 48,
        "country": "AU"
    },
    {
        "name": "Angela Snyder",
        "age": 27,
        "country": "UK"
    },
    {
        "name": "Logan Warren",
        "age": 51,
        "country": "UK"
    },
    {
        "name": "Jeffrey Watts",
        "age": 45,
        "country": "UK"
    },
    {
        "name": "Renee Brooks",
        "age": 19,
        "country": "AU"
    },
    {
        "name": "Nicholas Pacheco",
        "age": 45,
        "country": "CA"
    },
    {
        "name": "John Lowe",
        "age": 40,
        "country": "FR"
    },
    {
        "name": "Joshua Clark",
        "age": 47,
        "country": "BR"
    },
    {
        "name": "William Carrillo",
        "age": 33,
        "country": "DE"
    },
    {
        "name": "Crystal Davis",
        "age": 26,
        "country": "DE"
    },
    {
        "name": "Justin Nixon",
        "age": 43,
        "country": "AU"
    },
    {
        "name": "Kayla Allen",
        "age": 52,
        "country": "UK"
    },
    {
        "name": "Michael Williams",
        "age": 19,
        "country": "AU"
    },
    {
        "name": "Jonathan Romero",
        "age": 60,
        "country": "CA"
    },
    {
        "name": "Daniel Johnson",
        "age": 51,
        "country": "CA"
    },
    {
        "name": "John Miller",
        "age": 40,
        "country": "FR"
    },
    {
        "name": "Linda Robinson",
        "age": 23,
        "country": "AU"
    },
    {
        "name": "Victoria Santiago",
        "age": 42,
        "country": "CA"
    },
    {
        "name": "Philip Hughes",
        "age": 37,
        "country": "UK"
    },
    {
        "name": "James Ortega",
        "age": 49,
        "country": "UK"
    },
    {
        "name": "Jessica Burton",
        "age": 41,
        "country": "DE"
    },
    {
        "name": "Joshua Norman",
        "age": 51,
        "country": "JP"
    },
    {
        "name": "Lori Villarreal",
        "age": 22,
        "country": "BR"
    },
    {
        "name": "Robert George",
        "age": 54,
        "country": "CA"
    },
    {
        "name": "David Ball",
        "age": 47,
        "country": "FR"
    },
    {
        "name": "Kimberly Anderson",
        "age": 44,
        "country": "UK"
    },
    {
        "name": "Michael Wilson",
        "age": 60,
        "country": "CA"
    },
    {
        "name": "Gregory Davis",
        "age": 58,
        "country": "US"
    },
    {
        "name": "Shannon Moore",
        "age": 31,
        "country": "FR"
    },
    {
        "name": "Alyssa Stewart",
        "age": 26,
        "country": "JP"
    },
    {
        "name": "Brian Myers",
        "age": 58,
        "country": "BR"
    },
    {
        "name": "Thomas Smith",
        "age": 41,
        "country": "CA"
    },
    {
        "name": "Maria Gray",
        "age": 35,
        "country": "AU"
    },
    {
        "name": "John Hicks",
        "age": 37,
        "country": "AU"
    },
    {
        "name": "Allison Yang",
        "age": 35,
        "country": "UK"
    },
    {
        "name": "Amy Bartlett",
        "age": 34,
        "country": "AU"
    },
    {
        "name": "Ann Reynolds",
        "age": 26,
        "country": "CA"
    },
    {
        "name": "Tristan Thomas",
        "age": 23,
        "country": "UK"
    },
    {
        "name": "Jerry Elliott",
        "age": 31,
        "country": "JP"
    },
    {
        "name": "Jon Marshall",
        "age": 54,
        "country": "BR"
    },
    {
        "name": "Sarah Serrano",
        "age": 53,
        "country": "US"
    },
    {
        "name": "Katrina Smith",
        "age": 28,
        "country": "BR"
    },
    {
        "name": "Linda Carpenter",
        "age": 55,
        "country": "BR"
    },
    {
        "name": "Stanley Gill",
        "age": 35,
        "country": "US"
    },
    {
        "name": "Ryan Gutierrez",
        "age": 22,
        "country": "BR"
    },
    {
        "name": "Kathryn Morgan",
        "age": 18,
        "country": "US"
    },
    {
        "name": "Nicole Powers",
        "age": 30,
        "country": "FR"
    },
    {
        "name": "Kevin Mata",
        "age": 46,
        "country": "US"
    },
    {
        "name": "Leah Price",
        "age": 53,
        "country": "FR"
    },
    {
        "name": "Jennifer Watkins",
        "age": 49,
        "country": "AU"
    },
    {
        "name": "Amanda Wu",
        "age": 56,
        "country": "CA"
    },
    {
        "name": "Andrew Hall",
        "age": 37,
        "country": "DE"
    },
    {
        "name": "Jill Nelson",
        "age": 19,
        "country": "FR"
    },
    {
        "name": "Paul Rodriguez",
        "age": 59,
        "country": "CA"
    },
    {
        "name": "Jessica Humphrey",
        "age": 33,
        "country": "BR"
    },
    {
        "name": "Kristin Pruitt",
        "age": 43,
        "country": "BR"
    },
    {
        "name": "Sandra Jackson",
        "age": 30,
        "country": "DE"
    },
    {
        "name": "Jamie Johnson",
        "age": 33,
        "country": "DE"
    },
    {
        "name": "Brandon Hoffman",
        "age": 36,
        "country": "CA"
    },
    {
        "name": "John Anderson",
        "age": 25,
        "country": "BR"
    },
    {
        "name": "Ian Shaw",
        "age": 35,
        "country": "DE"
    },
    {
        "name": "Karen Williams",
        "age": 39,
        "country": "JP"
    },
    {
        "name": "Charles Martinez",
        "age": 60,
        "country": "AU"
    },
    {
        "name": "Bobby Stewart",
        "age": 24,
        "country": "BR"
    },
    {
        "name": "David Williams",
        "age": 54,
        "country": "UK"
    },
    {
        "name": "Joe Peck",
        "age": 32,
        "country": "CA"
    },
    {
        "name": "David Weber",
        "age": 33,
        "country": "CA"
    },
    {
        "name": "John Schultz",
        "age": 37,
        "country": "DE"
    },
    {
        "name": "Cheryl Davis",
        "age": 59,
        "country": "FR"
    },
    {
        "name": "Diana Anderson",
        "age": 56,
        "country": "CA"
    },
    {
        "name": "John Anderson",
        "age": 27,
        "country": "BR"
    },
    {
        "name": "Robert Strickland",
        "age": 55,
        "country": "AU"
    },
    {
        "name": "Charles Garcia",
        "age": 44,
        "country": "FR"
    },
    {
        "name": "Adam Andrade",
        "age": 33,
        "country": "AU"
    },
    {
        "name": "Jacob Harris",
        "age": 18,
        "country": "BR"
    },
    {
        "name": "Gloria Burton",
        "age": 55,
        "country": "UK"
    },
    {
        "name": "Amanda Reid",
        "age": 36,
        "country": "UK"
    },
    {
        "name": "Kristen Velez",
        "age": 50,
        "country": "CA"
    },
    {
        "name": "Alejandra Suarez",
        "age": 52,
        "country": "UK"
    },
    {
        "name": "Jennifer Henderson",
        "age": 40,
        "country": "JP"
    },
    {
        "name": "Robin Downs",
        "age": 33,
        "country": "DE"
    },
    {
        "name": "Ruth Leonard",
        "age": 49,
        "country": "AU"
    },
    {
        "name": "Vanessa Fuller",
        "age": 27,
        "country": "JP"
    },
    {
        "name": "Gabriela Dawson",
        "age": 37,
        "country": "AU"
    },
    {
        "name": "Susan Townsend",
        "age": 23,
        "country": "DE"
    },
    {
        "name": "Lisa Chang",
        "age": 29,
        "country": "DE"
    },
    {
        "name": "John Brown",
        "age": 29,
        "country": "DE"
    },
    {
        "name": "Elizabeth Taylor",
        "age": 39,
        "country": "FR"
    },
    {
        "name": "Melinda Ortiz",
        "age": 47,
        "country": "CA"
    },
    {
        "name": "Jason Taylor",
        "age": 24,
        "country": "US"
    },
    {
        "name": "Harold Sims",
        "age": 43,
        "country": "DE"
    },
    {
        "name": "Melvin Johnson",
        "age": 47,
        "country": "JP"
    },
    {
        "name": "Jose Davis",
        "age": 60,
        "country": "UK"
    },
    {
        "name": "Ellen Rodriguez",
        "age": 36,
        "country": "AU"
    },
    {
        "name": "Mary Miller",
        "age": 54,
        "country": "AU"
    },
    {
        "name": "Tyler Montoya",
        "age": 49,
        "country": "CA"
    },
    {
        "name": "Renee Gates",
        "age": 19,
        "country": "UK"
    },
    {
        "name": "Richard Moses",
        "age": 43,
        "country": "US"
    },
    {
        "name": "Christopher Washington",
        "age": 60,
        "country": "UK"
    },
    {
        "name": "William Stanley",
        "age": 27,
        "country": "FR"
    },
    {
        "name": "Ariel Turner",
        "age": 39,
        "country": "CA"
    },
    {
        "name": "Jacob Ochoa",
        "age": 57,
        "country": "AU"
    },
    {
        "name": "Kyle Rivera",
        "age": 33,
        "country": "JP"
    },
    {
        "name": "Brian Jones",
        "age": 34,
        "country": "UK"
    },
    {
        "name": "Darrell Gomez",
        "age": 50,
        "country": "BR"
    },
    {
        "name": "Nicole Hull",
        "age": 57,
        "country": "UK"
    },
    {
        "name": "Colleen Velez",
        "age": 20,
        "country": "BR"
    },
    {
        "name": "Crystal Schmidt",
        "age": 29,
        "country": "FR"
    },
    {
        "name": "Kelly Henderson",
        "age": 18,
        "country": "AU"
    },
    {
        "name": "Jared Davis",
        "age": 54,
        "country": "UK"
    },
    {
        "name": "Nathaniel Taylor",
        "age": 18,
        "country": "JP"
    },
    {
        "name": "Lisa Jones",
        "age": 52,
        "country": "BR"
    },
    {
        "name": "Courtney Schmidt",
        "age": 23,
        "country": "CA"
    },
    {
        "name": "Adam Stewart",
        "age": 39,
        "country": "UK"
    },
    {
        "name": "Stacy Ritter",
        "age": 52,
        "country": "UK"
    },
    {
        "name": "Cathy Mills",
        "age": 60,
        "country": "BR"
    },
    {
        "name": "Jason Williams",
        "age": 54,
        "country": "UK"
    },
    {
        "name": "Jason Kim II",
        "age": 54,
        "country": "US"
    },
    {
        "name": "Cynthia Hahn",
        "age": 58,
        "country": "DE"
    },
    {
        "name": "Briana Ramos",
        "age": 36,
        "country": "FR"
    },
    {
        "name": "Whitney Kemp",
        "age": 37,
        "country": "US"
    },
    {
        "name": "Theodore Kerr",
        "age": 58,
        "country": "AU"
    },
    {
        "name": "Douglas Maddox",
        "age": 56,
        "country": "UK"
    },
    {
        "name": "Charles Lyons",
        "age": 47,
        "country": "BR"
    },
    {
        "name": "Arthur York",
        "age": 40,
        "country": "AU"
    },
    {
        "name": "Lori Vaughn",
        "age": 34,
        "country": "AU"
    }
]